whiteboxgui/__init__.py
whiteboxgui/whiteboxgui.py
whiteboxgui/data/whitebox_tools.json
whiteboxgui-2.3.0.dist-info/LICENSE
whiteboxgui-2.3.0.dist-info/METADATA
whiteboxgui-2.3.0.dist-info/WHEEL
whiteboxgui-2.3.0.dist-info/dependency_links.txt
whiteboxgui-2.3.0.dist-info/top_level.txt
whiteboxgui-2.3.0.dist-info/RECORD
