Metadata-Version: 2.1
Name: whiteboxgui
Version: 2.3.0
Summary: An interactive GUI for whitebox-tools in a Jupyter-based environment
Home-page: https://github.com/giswqs/whiteboxgui
Author: Qiusheng Wu
Author-email: giswqs@gmail.com
License: MIT license
Keywords: whiteboxgui
Classifier: Development Status :: 2 - Pre-Alpha
Classifier: Intended Audience :: Developers
Classifier: License :: OSI Approved :: MIT License
Classifier: Natural Language :: English
Classifier: Programming Language :: Python :: 3
Classifier: Programming Language :: Python :: 3.7
Classifier: Programming Language :: Python :: 3.8
Classifier: Programming Language :: Python :: 3.9
Classifier: Programming Language :: Python :: 3.10
Classifier: Programming Language :: Python :: 3.11
Requires-Python: >=3.5
License-File: LICENSE
